jupyterhub_inithooks/__init__.py
jupyterhub_inithooks-0.1.dist-info/LICENSE
jupyterhub_inithooks-0.1.dist-info/METADATA
jupyterhub_inithooks-0.1.dist-info/WHEEL
jupyterhub_inithooks-0.1.dist-info/entry_points.txt
jupyterhub_inithooks-0.1.dist-info/top_level.txt
jupyterhub_inithooks-0.1.dist-info/RECORD
